lambda_utils/__init__.py
lambda_utils/collections.py
lambda_utils/core.py
lambda_utils/functional.py
lambda_u-0.1.0.dist-info/LICENSE
lambda_u-0.1.0.dist-info/METADATA
lambda_u-0.1.0.dist-info/WHEEL
lambda_u-0.1.0.dist-info/top_level.txt
lambda_u-0.1.0.dist-info/RECORD
