Metadata-Version: 2.1
Name: lambda_u
Version: 0.1.0
Summary: Python lambda extension library
Home-page: https://github.com/Soul2024tk/lambda
Author: Soul2024tk
Author-email: soulcodingyanhun@gmail.com
Classifier: Programming Language :: Python :: 3
Classifier: License :: OSI Approved :: MIT License
Classifier: Operating System :: OS Independent
Requires-Python: >=3.6
License-File: LICENSE
